pyhelayerslite-1.5.5.3.dist-info/RECORD
pyhelayerslite-1.5.5.3.dist-info/METADATA
pyhelayerslite-1.5.5.3.dist-info/top_level.txt
pyhelayerslite-1.5.5.3.dist-info/LICENSE
pyhelayerslite-1.5.5.3.dist-info/WHEEL
pyhelayerslite/__init__.py
pyhelayerslite/_pyhelayerslite_cppwrappers.cpython-38-x86_64-linux-gnu.so
pyhelayerslite/libs/_dummy.cpython-38-x86_64-linux-gnu.so
pyhelayerslite/resources/default_helayers_config.json
pyhelayerslite/resources/optimizer/palisade.json
pyhelayerslite/resources/optimizer/openfhe-ckks.json
pyhelayerslite/resources/optimizer/seal.json
pyhelayerslite/resources/optimizer/lattigo.json
pyhelayerslite/resources/er/nick_to_name.csv
pyhelayerslite/resources/er/README.md
pyhelayerslite.libs/libgomp-a34b3233.so.1.0.0
pyhelayerslite.libs/libboost_filesystem-3bb8adbd.so.1.72.0
pyhelayerslite.libs/libcrypto-ee067a53.so.1.1
