Metadata-Version: 2.1
Name: pyhelayerslite
Version: 1.5.5.3
Summary: HElayers SDK for homomorphic encryption
Home-page: UNKNOWN
Author: IBM
Author-email: FHEstart@us.ibm.com
License: Community edition license for non-commercial use
Keywords: helayers,fhe,ai
Platform: UNKNOWN
Classifier: License :: Other/Proprietary License
Classifier: Intended Audience :: Developers
Classifier: Intended Audience :: Science/Research
Classifier: Intended Audience :: Information Technology
Classifier: Topic :: Security :: Cryptography
Classifier: Operating System :: OS Independent
Requires-Dist: numpy>=1.14.5
Provides-Extra: ext
Requires-Dist: scikit-learn>=0.20.0; extra == "ext"
Requires-Dist: sklearn-json>=0.1.0; extra == "ext"
Requires-Dist: tensorflow>=2.0.0; extra == "ext"
